itk_iomgh.libs/libtbb-a0c974ac.so.12.3
itk_iomgh-1.1.1.dist-info/WHEEL
itk_iomgh-1.1.1.dist-info/RECORD
itk_iomgh-1.1.1.dist-info/METADATA
itk_iomgh-1.1.1.dist-info/top_level.txt
itk/itkMGHImageIOPython.py
itk/_MGHIOPython.so
itk/MGHIOPython.py
itk/Configuration/MGHIOConfig.py
itk/Configuration/MGHIO_snake_case.py
