Metadata-Version: 2.1
Name: itk-iomgh
Version: 1.1.1
Summary: An ITK module to support input and output of the MGH file format.
Home-page: https://itk.org/
Author: Insight Software Consortium
Author-email: community@itk.org
License: Apache
Download-URL: https://github.com/Slicer/itkMGHImageIO.git
Keywords: ITK InsightToolkit MGH Slicer
Platform: UNKNOWN
Classifier: License :: OSI Approved :: Apache Software License
Classifier: Programming Language :: Python
Classifier: Programming Language :: C++
Classifier: Development Status :: 4 - Beta
Classifier: Intended Audience :: Developers
Classifier: Intended Audience :: Education
Classifier: Intended Audience :: Healthcare Industry
Classifier: Intended Audience :: Science/Research
Classifier: Topic :: Scientific/Engineering
Classifier: Topic :: Scientific/Engineering :: Medical Science Apps.
Classifier: Topic :: Scientific/Engineering :: Information Analysis
Classifier: Topic :: Software Development :: Libraries
Classifier: Operating System :: Android
Classifier: Operating System :: Microsoft :: Windows
Classifier: Operating System :: POSIX
Classifier: Operating System :: Unix
Classifier: Operating System :: MacOS
Requires-Dist: itk (>=5.3rc3)
